lab001/lab001.v

module lab001(
input A,
input B,
input Ci,
output S,
output Co

);

wire xor_1;
wire and_1;
wire and_2;

assign xor_1 = A^B;
assign and_1 = A&B;
assign and_2 = xor_1 & Ci;

assign S = xor_1 ^Ci;
assign Co = and_1 | and_2;

endmodule

lab001/src/lab001tb.v
`include "lab001.v" // Se llama el .v donde va la logica
`timescale 1ps/1ps 

module lab001tb(); //EL modulo lo llamas como quieras aca lo llame igual que el archivo

reg A_tb; // Entradas de tu logica del archivo anterior
reg B_tb; // mi segunda entrada
reg Ci_tb; // Tercera entrada
wire S_; //ESTAN SON LAS SALIDAS
wire Co_; //SALIDAS


//AQUI LLAMAMOS LAS VARIBALES CON LA LOGICA ANTERIAR ASI PRIMERO LA DEL LAB.v antes un punto .ENTRADA(ENTRADA TESTBECH)-- ENTRADA DEL TEST
//LA IDEA ES ENLAZARLO


lab001 uut(
    .A(A_tb),
    .B(B_tb),
    .Ci(Ci_tb),
    .S(S_),
    .Co(Co_)
);
// AQUI LE DAMOS LOS VALORES QUE QUEREMOS
initial begin
A_tb = 0;
B_tb = 0;
Ci_tb = 0;
#100;
A_tb = 0;
B_tb = 0; 
Ci_tb = 1;
#100
A_tb = 0;
B_tb = 1; 
Ci_tb = 0;
#100
A_tb = 0;
B_tb = 1; 
Ci_tb = 1;
#100
A_tb = 1;
B_tb = 0; 
Ci_tb = 0;
#100
A_tb = 1;
B_tb = 0; 
Ci_tb = 1;
#100
A_tb = 1;
B_tb = 1; 
Ci_tb = 0;
#100
A_tb = 1;
B_tb = 1; 
Ci_tb = 1;
// PARA PODER CREAR EL VCD QUE ES LA SIMULACIÓN
end

initial begin: TEST_CASE
    $dumpfile("lab001.vcd");
    $dumpvars(-1,uut);
    #800 $finish;
end


endmodule

lab001/src/build/lab001.vcd
$date
	Wed Mar 13 10:16:36 2024
$end
$version
	Icarus Verilog
$end
$timescale
	1ps
$end
$scope module lab001tb $end
$scope module uut $end
$var wire 1 ! A $end
$var wire 1 " B $end
$var wire 1 # Ci $end
$var wire 1 $ Co $end
$var wire 1 % S $end
$var wire 1 & and_1 $end
$var wire 1 ' and_2 $end
$var wire 1 ( xor_1 $end
$upscope $end
$upscope $end
$enddefinitions $end
#0
$dumpvars
0(
0'
0&
0%
0$
0#
0"
0!
$end
#100
1%
1#
#200
1(
0#
1"
#300
1$
1'
0%
1#
#400
0$
0'
1%
0#
0"
1!
#500
1$
1'
0%
1#
#600
0'
0(
1&
0#
1"
#700
1%
1#
