lab001/lab001.v

module lab001(
input A,
input B,
input Ci,
output S,
output Co

);

wire xor_1;
wire and_1;
wire and_2;

assign xor_1 = A^B;
assign and_1 = A&B;
assign and_2 = xor_1 & Ci;

assign S = xor_1 ^Ci;
assign Co = and_1 | and_2;

endmodule

LAB002/src/LAB002.v

module sum4b(a, b, ci, s, co);

input [3:0] a;
input [3:0] b;
input ci;
output [3:0] s;
output co;

wire C1,C2,C3;

lab001 sum0 (.A(a[0]), .B(b[0]), .Ci(1'b0), .S(s[0]), .Co(C1));
lab001 sum1 (.A(a[1]), .B(b[1]), .Ci(C1), .S(s[1]), .Co(C2));
lab001 sum2 (.A(a[2]), .B(b[2]), .Ci(C2), .S(s[2]), .Co(C3));
lab001 sum3 (.A(a[3]), .B(b[3]), .Ci(C3), .S(s[3]), .Co(co));

endmodule

LAB002/src/sum4b_tb.v
`include "LAB002.v" // logica general

module sum4b_tb();

    reg [3:0] a_tb;    // Entrada a de 4 bits registros
    reg [3:0] b_tb;    // Entrada b de 4 bits
    reg ci_tb;         // Entrada de acarreo de 1 bit
    wire [3:0] s_tb;   // Salida s de 4 bits se modifican
    wire co_tb;        // Salida de acarreo de 1 bit

    // Instanciación del módulo sum4b bajo prueba
    sum4b uut (   //Se instancia el modulo de la logica general 
        .a(a_tb),
        .b(b_tb),
        .ci(ci_tb),
        .s(s_tb),
        .co(co_tb)
    );

    // Inicialización de las entradas
    initial begin
        // Caso de prueba 1
        a_tb = 4'b0000;
        b_tb = 4'b0000;
        ci_tb = 1'b0;
        #10;

        // Caso de prueba 2
        a_tb = 4'b0001;
        b_tb = 4'b0001;
        ci_tb = 1'b0;
        #10;

        // Caso de prueba 3
        a_tb = 4'b0010;
        b_tb = 4'b0010;
        ci_tb = 1'b0;
        #10;

        // Caso de prueba 4
        a_tb = 4'b0011;
        b_tb = 4'b0011;
        ci_tb = 1'b0;
        #10;

        // Caso de prueba 5
        a_tb = 4'b0100;
        b_tb = 4'b0100;
        ci_tb = 1'b0;
        #10;

        // Caso de prueba 6
        a_tb = 4'b0101;
        b_tb = 4'b0101;
        ci_tb = 1'b0;
        #10;

        // Caso de prueba 7
        a_tb = 4'b0110;
        b_tb = 4'b0110;
        ci_tb = 1'b0;
        #10;

        // Caso de prueba 8
        a_tb = 4'b0111;
        b_tb = 4'b0111;
        ci_tb = 1'b0;
        #10;

        // Caso de prueba 9
        a_tb = 4'b1000;
        b_tb = 4'b1000;
        ci_tb = 1'b0;
        #10;

        // Caso de prueba 10
        a_tb = 4'b1001;
        b_tb = 4'b1001;
        ci_tb = 1'b0;
        #10;

        // Caso de prueba 11
        a_tb = 4'b1010;
        b_tb = 4'b1010;
        ci_tb = 1'b0;
        #10;

        // Caso de prueba 12
        a_tb = 4'b1011;
        b_tb = 4'b1011;
        ci_tb = 1'b0;
        #10;

        // Caso de prueba 13
        a_tb = 4'b1100;
        b_tb = 4'b1100;
        ci_tb = 1'b0;
        #10;

        // Caso de prueba 14
        a_tb = 4'b1101;
        b_tb = 4'b1101;
        ci_tb = 1'b0;
        #10;

        // Caso de prueba 15
        a_tb = 4'b1110;
        b_tb = 4'b1110;
        ci_tb = 1'b0;
        #10;

        // Caso de prueba 16
        a_tb = 4'b1111;
        b_tb = 4'b1111;
        ci_tb = 1'b0;
        #10;

        // Finalización de la simulación
        
    end

    // Guardar la simulación en un archivo VCD
    initial begin
        $dumpfile("sum4b_tb.vcd");
        $dumpvars(-1, uut); //Averiguar ??

        #240 $finish;
        
        

    end

endmodule

LAB002/src/build/sum4b_tb.vcd
$date
	Wed Apr 24 09:29:57 2024
$end
$version
	Icarus Verilog
$end
$timescale
	1s
$end
$scope module sum4b_tb $end
$scope module uut $end
$var wire 4 ! a [3:0] $end
$var wire 4 " b [3:0] $end
$var wire 1 # ci $end
$var wire 4 $ s [3:0] $end
$var wire 1 % co $end
$var wire 1 & C3 $end
$var wire 1 ' C2 $end
$var wire 1 ( C1 $end
$scope module sum0 $end
$var wire 1 ) A $end
$var wire 1 * B $end
$var wire 1 + Ci $end
$var wire 1 ( Co $end
$var wire 1 , S $end
$var wire 1 - and_1 $end
$var wire 1 . and_2 $end
$var wire 1 / xor_1 $end
$upscope $end
$scope module sum1 $end
$var wire 1 0 A $end
$var wire 1 1 B $end
$var wire 1 ( Ci $end
$var wire 1 ' Co $end
$var wire 1 2 S $end
$var wire 1 3 and_1 $end
$var wire 1 4 and_2 $end
$var wire 1 5 xor_1 $end
$upscope $end
$scope module sum2 $end
$var wire 1 6 A $end
$var wire 1 7 B $end
$var wire 1 ' Ci $end
$var wire 1 & Co $end
$var wire 1 8 S $end
$var wire 1 9 and_1 $end
$var wire 1 : and_2 $end
$var wire 1 ; xor_1 $end
$upscope $end
$scope module sum3 $end
$var wire 1 < A $end
$var wire 1 = B $end
$var wire 1 & Ci $end
$var wire 1 % Co $end
$var wire 1 > S $end
$var wire 1 ? and_1 $end
$var wire 1 @ and_2 $end
$var wire 1 A xor_1 $end
$upscope $end
$upscope $end
$upscope $end
$enddefinitions $end
#0
$dumpvars
0A
0@
0?
0>
0=
0<
0;
0:
09
08
07
06
05
04
03
02
01
00
0/
0.
0-
0,
0+
0*
0)
0(
0'
0&
0%
b0 $
0#
b0 "
b0 !
$end
#10
b10 $
12
1(
1-
1*
1)
b1 "
b1 !
#20
02
b100 $
18
0(
1'
0-
13
0*
11
0)
10
b10 "
b10 !
#30
b110 $
12
1(
1-
1*
1)
b11 "
b11 !
#40
02
08
b1000 $
1>
0(
0'
1&
0-
03
19
0*
01
17
0)
00
16
b100 "
b100 !
#50
b1010 $
12
1(
1-
1*
1)
b101 "
b101 !
#60
02
b1100 $
18
0(
1'
0-
13
0*
11
0)
10
b110 "
b110 !
#70
b1110 $
12
1(
1-
1*
1)
b111 "
b111 !
#80
02
08
b0 $
0>
0(
0'
0&
1%
0-
03
09
1?
0*
01
07
1=
0)
00
06
1<
b1000 "
b1000 !
#90
b10 $
12
1(
1-
1*
1)
b1001 "
b1001 !
#100
02
b100 $
18
0(
1'
0-
13
0*
11
0)
10
b1010 "
b1010 !
#110
b110 $
12
1(
1-
1*
1)
b1011 "
b1011 !
#120
02
08
b1000 $
1>
0(
0'
1&
0-
03
19
0*
01
17
0)
00
16
b1100 "
b1100 !
#130
b1010 $
12
1(
1-
1*
1)
b1101 "
b1101 !
#140
02
b1100 $
18
0(
1'
0-
13
0*
11
0)
10
b1110 "
b1110 !
#150
b1110 $
12
1(
1-
1*
1)
b1111 "
b1111 !
